cjenc/__init__.py
cjenc/custom_serializable.py
cjenc/customizable_json_encoder.py
cjenc/sample.py
customizable_json_encoder-0.0.4.dist-info/LICENSE
customizable_json_encoder-0.0.4.dist-info/METADATA
customizable_json_encoder-0.0.4.dist-info/WHEEL
customizable_json_encoder-0.0.4.dist-info/top_level.txt
customizable_json_encoder-0.0.4.dist-info/RECORD
