Metadata-Version: 2.1
Name: customizable-json-encoder
Version: 0.0.4
Summary: Customizable JSON Encoder for python. module name is cjenc.
Author-email: LostEnryu <enryu.lost1n4rest@gmail.com>
Maintainer-email: LostEnryu <enryu.lost1n4rest@gmail.com>
License: MIT License
Project-URL: Repository, https://github.com/LostEnryu/CustomizableJsonEncoder.git
Project-URL: Issues, https://github.com/LostEnryu/CustomizableJsonEncoder/issues
Keywords: custom,json,encoder,YasueShuta
Classifier: Development Status :: 4 - Beta
Classifier: Intended Audience :: Developers
Classifier: Topic :: Software Development :: Libraries
Classifier: License :: OSI Approved :: MIT License
Classifier: Programming Language :: Python :: 3
Classifier: Programming Language :: Python :: 3.8
Classifier: Programming Language :: Python :: 3.11
Requires-Python: >=3.8
License-File: LICENSE
